rio_glui/__init__.py
rio_glui/raster.py
rio_glui/server.py
rio_glui/scripts/__init__.py
rio_glui/scripts/cli.py
rio_glui/static/jquery-3.3.1.min.js
rio_glui/static/jquery.console.js
rio_glui/templates/index.html
rio_glui/templates/playground.html
rio_glui-1.0.6.dist-info/LICENSE
rio_glui-1.0.6.dist-info/METADATA
rio_glui-1.0.6.dist-info/WHEEL
rio_glui-1.0.6.dist-info/entry_points.txt
rio_glui-1.0.6.dist-info/top_level.txt
rio_glui-1.0.6.dist-info/RECORD
