Metadata-Version: 2.1
Name: rio-glui
Version: 1.0.6
Summary: Inspect CloudOptimized Geotiff using Mapbox GL JS
Home-page: https://github.com/mapbox/rio-glui
Author: Damon Burgett
Author-email: damon@mapbox.com
License: BSD
Keywords: COGEO CloudOptimized Geotiff rasterio Mapbox-GL
Platform: UNKNOWN
Classifier: Intended Audience :: Information Technology
Classifier: Intended Audience :: Science/Research
Classifier: License :: OSI Approved :: BSD License
Classifier: Programming Language :: Python :: 3.6
Classifier: Programming Language :: Python :: 2.7
Classifier: Topic :: Scientific/Engineering :: GIS
Requires-Dist: tornado (==4.5.3)
Requires-Dist: rio-tiler (~=1.0)
Requires-Dist: click
Requires-Dist: rio-color
Provides-Extra: dev
Requires-Dist: pytest ; extra == 'dev'
Requires-Dist: pytest-cov ; extra == 'dev'
Requires-Dist: pre-commit ; extra == 'dev'
Provides-Extra: test
Requires-Dist: mock ; extra == 'test'
Requires-Dist: pytest ; extra == 'test'
Requires-Dist: pytest-cov ; extra == 'test'
